convert_tif_to_png/__init__.py
convert_tif_to_png/__main__.py
convert_tif_to_png/main.py
convert_tif_to_png-1.0.6.dist-info/LICENSE
convert_tif_to_png-1.0.6.dist-info/METADATA
convert_tif_to_png-1.0.6.dist-info/WHEEL
convert_tif_to_png-1.0.6.dist-info/entry_points.txt
convert_tif_to_png-1.0.6.dist-info/RECORD
