Metadata-Version: 2.1
Name: convert-tif-to-png
Version: 1.0.6
Summary: A utility to convert TIF images to PNG with optional resizing and renaming. Preserve quality of photos from apps like Adobe Lightroom while formatting files for social media sharing.
License: MIT
Requires-Python: >=3.5
Classifier: Development Status :: 4 - Beta
Classifier: Intended Audience :: Developers
Classifier: License :: OSI Approved :: MIT License
Classifier: Operating System :: OS Independent
Classifier: Programming Language :: Python :: 3
Classifier: Programming Language :: Python :: 3.5
Classifier: Programming Language :: Python :: 3.6
Classifier: Programming Language :: Python :: 3.7
Classifier: Programming Language :: Python :: 3.8
Classifier: Programming Language :: Python :: 3.9
Classifier: Programming Language :: Python :: 3.10
Classifier: Programming Language :: Python :: 3.11
Classifier: Programming Language :: Python :: 3.12
Classifier: Topic :: Multimedia :: Graphics :: Graphics Conversion
Requires-Dist: pillow (==8.4.0)
